MANIFEST.in
README.md
README.rst
setup.py
nanoraw/__init__.py
nanoraw/__main__.py
nanoraw/nanoraw_helper.py
nanoraw/nanoraw_stats.py
nanoraw/option_parsers.py
nanoraw/plot_commands.py
nanoraw/resquiggle.py
nanoraw/text_output_commands.py
nanoraw.egg-info/PKG-INFO
nanoraw.egg-info/SOURCES.txt
nanoraw.egg-info/dependency_links.txt
nanoraw.egg-info/entry_points.txt
nanoraw.egg-info/requires.txt
nanoraw.egg-info/top_level.txt
nanoraw/R_scripts/plotGroupComp.R
nanoraw/R_scripts/plotKmerDist.R
nanoraw/R_scripts/plotMotifStats.R
nanoraw/R_scripts/plotMultiReadCorr.R
nanoraw/R_scripts/plotReadCorr.R
nanoraw/R_scripts/plotSigMDS.R
nanoraw/R_scripts/plotSingleRun.R