Metadata-Version: 1.0
Name: nanoraw
Version: 0.4.1
Summary: Analysis of nanopore sequencing data.
Home-page: https://github.com/marcus1487/nanoraw
Author: Marcus Stoiber
Author-email: mhstoiber@lbl.gov
License: BSD
Keywords: nanopore high-throughput sequencing correction genome
Platform: UNKNOWN
